{
	"forge_marker": 1,
	"variants": {
		"half": {
			"bottom": { "model": "half_slab" },
			"top": { "model": "upper_slab" }
		},
		"type": {
			"gneiss": {
				"textures": {
					"bottom": "undergroundbiomes:blocks/gneiss_cobble",
					"top": "undergroundbiomes:blocks/gneiss_cobble",
					"side": "undergroundbiomes:blocks/gneiss_cobble"
				}
			},
			"eclogite": {
				"textures": {
					"bottom": "undergroundbiomes:blocks/eclogite_cobble",
					"top": "undergroundbiomes:blocks/eclogite_cobble",
					"side": "undergroundbiomes:blocks/eclogite_cobble"
				}
			},
			"marble": {
				"textures": {
					"bottom": "undergroundbiomes:blocks/marble_cobble",
					"top": "undergroundbiomes:blocks/marble_cobble",
					"side": "undergroundbiomes:blocks/marble_cobble"
				}
			},
			"quartzite": {
				"textures": {
					"bottom": "undergroundbiomes:blocks/quartzite_cobble",
					"top": "undergroundbiomes:blocks/quartzite_cobble",
					"side": "undergroundbiomes:blocks/quartzite_cobble"
				}
			},
			"blueschist": {
				"textures": {
					"bottom": "undergroundbiomes:blocks/blueschist_cobble",
					"top": "undergroundbiomes:blocks/blueschist_cobble",
					"side": "undergroundbiomes:blocks/blueschist_cobble"
				}
			},
			"greenschist": {
				"textures": {
					"bottom": "undergroundbiomes:blocks/greenschist_cobble",
					"top": "undergroundbiomes:blocks/greenschist_cobble",
					"side": "undergroundbiomes:blocks/greenschist_cobble"
				}
			},
			"soapstone": {
				"textures": {
					"bottom": "undergroundbiomes:blocks/soapstone_cobble",
					"top": "undergroundbiomes:blocks/soapstone_cobble",
					"side": "undergroundbiomes:blocks/soapstone_cobble"
				}
			},
			"migmatite": {
				"textures": {
					"bottom": "undergroundbiomes:blocks/migmatite_cobble",
					"top": "undergroundbiomes:blocks/migmatite_cobble",
					"side": "undergroundbiomes:blocks/migmatite_cobble"
				}
			}
		}
	}
}
